[{
    "name": "Jason",
    "last_Name": "Mop",
    "username": "FernandoWick",
    "password": "Test123*",
    "coorname": "Anna",
    "coorlastname": "Sweet",
    "phone": "9847638734",
    "email": "gabriel.gomez@10pearls.com",
    "learn_about": "hi, my name is peter I have bought the kiwi van. I have a few questions for you about and other things could you be able to get back to me thanks.  In response to your voice mail about the caller s phone not syncing with Facebook. I am half Cypriot and a half from Finland I have bought the kiwi van.1Each event created needs a description input box. This would allow the admin coordinator to input instructions regarding the event and its location that the participant can view on the calendar. For example: This workshop is discussion-based. It will take place at EJ HQ. Please park on the road. The door is located on the side of the building and the door code is 3322.Show next to the chat, an eye icon that when we click it will hide this message and the icon will change. When you hide a message, it will be a little alpha, unlike the other messages.Adhere to UI update requests made on 12in the Staging Environment Feedback document on Basecamp.5th-8th grade student with a high-achieving characters"
  }]